{
  "meta": {
    "label": "23C quiet HCN E scan"
  },
  "base": {
    "morphology": {
      "length_um": 10.0,
      "diam_um": 31.830988618379067,
      "cm_uF_cm2": 1.0
    },
    "simulation": {
      "dt_ms": 0.025,
      "duration_ms": 10.0,
      "v_init_mV": -80.0,
      "temperature_celsius": 23.0
    },
    "stimulus": {
      "kind": "dc",
      "delay_ms": 5.0,
      "dur_ms": 5.0,
      "amp_nA": 0.1
    },
    "leak": {
      "enabled": false,
      "g_S_cm2": 0.0,
      "e_mV": -65.0
    },
    "channel_params": {
      "g_max_S_cm2": 0.0001,
      "E_mV": -34.4
    }
  },
  "group": {
    "group_id": "e_scan",
    "description": "Quiet HCN run with reversal-potential scan.",
    "sweep_axes": {
      "channel_params.E_mV": [
        -45.0,
        -34.4,
        -25.0,
        -20.0
      ]
    }
  },
  "outputs": {
    "plot": false
  }
}
